Codes/Verilog/demux_8x1.v
module demux (
    input wire in,
    input wire [0:2] s,
    output wire [0:7] y
);

    assign y[0] = in & (~s[0]) & (~s[1]) & (~s[2]);
    assign y[1] = in & (~s[0]) & (~s[1]) & (s[2]);
    assign y[2] = in & (~s[0]) & (s[1]) & (~s[2]);
    assign y[3] = in & (~s[0]) & (s[1]) & (s[2]);
    assign y[4] = in & (s[0]) & (~s[1]) & (~s[2]);
    assign y[5] = in & (s[0]) & (~s[1]) & (s[2]);
    assign y[6] = in & (s[0]) & (s[1]) & (~s[2]);
    assign y[7] = in & (s[0]) & (s[1]) & (s[2]);

endmodule


`timescale 1ns / 1ps
module tb_demux;

    reg in;
    reg [0:2] s;
    wire [0:7] y;

    demux uut (
        .in(in),
        .s(s),
        .y(y)
    );

    initial begin
        $dumpfile("demux.vcd");
        $dumpvars(0, tb_demux);

        $display("Time\tIn\tSel\t\tOutput");
        $monitor("%0t\t%b\t%b\t%b", $time, in, s, y);

        in = 1'b1;

        s = 3'b000; #10;
        s = 3'b001; #10;
        s = 3'b010; #10;
        s = 3'b011; #10;
        s = 3'b100; #10;
        s = 3'b101; #10;
        s = 3'b110; #10;
        s = 3'b111; #10;

        in = 1'b0; // test input low, all outputs should be 0
        s = 3'b000; #10;

        $finish;
    end

endmodule

Codes/Verilog/build/demux.vcd
$date
	Fri Sep 26 10:37:06 2025
$end
$version
	Icarus Verilog
$end
$timescale
	1ps
$end
$scope module tb_demux $end
$var wire 8 ! y [0:7] $end
$var reg 1 " in $end
$var reg 3 # s [0:2] $end
$scope module uut $end
$var wire 1 " in $end
$var wire 3 $ s [0:2] $end
$var wire 8 % y [0:7] $end
$upscope $end
$upscope $end
$enddefinitions $end
$comment Show the parameter values. $end
$dumpall
$end
#0
$dumpvars
b10000000 %
b0 $
b0 #
1"
b10000000 !
$end
#10000
b1000000 !
b1000000 %
b1 #
b1 $
#20000
b100000 !
b100000 %
b10 #
b10 $
#30000
b10000 !
b10000 %
b11 #
b11 $
#40000
b1000 !
b1000 %
b100 #
b100 $
#50000
b100 !
b100 %
b101 #
b101 $
#60000
b10 !
b10 %
b110 #
b110 $
#70000
b1 !
b1 %
b111 #
b111 $
#80000
b0 !
b0 %
b0 #
b0 $
0"
