Codes/Verilog/dflipflop.v
module D_flipflop (
    input D,          
    input clk,        
    input reset,      
    output reg Q      
);

always @(posedge clk or posedge reset) begin
    if (reset)
        Q <= 1'b0;    
    else
        Q <= D;       
end

endmodule


module testbench;
    reg D, clk, reset;
    wire Q;

    D_flipflop uut (
        .D(D),
        .clk(clk),
        .reset(reset),
        .Q(Q)
    );

    always #5 clk = ~clk;

    initial begin
        $dumpfile("dflipflop2.vcd");
        $dumpvars(0, testbench);
    end

    initial begin
        clk = 0;
        reset = 1;
        D = 0;

        $display("Time\tclk\tr\tD\tQ");
        $monitor("%0t\t%b\t%b\t%b\t%b", $time, clk, reset, D, Q);

        #10 reset = 0;  
        #10 D = 1;      
        #10 D = 0;      
        #10 D = 1;      
        #20 reset = 1;  
        #10 reset = 0;  
        #20 $finish;    
    end

endmodule

Codes/Verilog/build/dflipflop.vcd
$date
	Fri Oct 10 11:21:53 2025
$end
$version
	Icarus Verilog
$end
$timescale
	1s
$end
$scope module testbench $end
$var wire 1 ! Q $end
$var reg 1 " D $end
$var reg 1 # clk $end
$var reg 1 $ reset $end
$scope module uut $end
$var wire 1 " D $end
$var wire 1 # clk $end
$var wire 1 $ reset $end
$var reg 1 ! Q $end
$upscope $end
$upscope $end
$enddefinitions $end
$comment Show the parameter values. $end
$dumpall
$end
#0
$dumpvars
1$
0#
0"
0!
$end
#5
1#
#10
0#
0$
#15
1#
#20
0#
1"
#25
1!
1#
#30
0#
0"
#35
0!
1#
#40
0#
1"
#45
1!
1#
#50
0#
#55
1#
#60
0!
0#
1$
#65
1#
#70
0#
0$
#75
1!
1#
