Codes/Verilog/fulladder_using_nand.v
module full_adder_using_nand(input a, input b, input c, output Sum, output Carry);
    wire w1, w2, w3, w4, w5, w6, w7;       

    nand nand1(w1, a, b);
    nand nand2(w2, a, w1);
    nand nand3(w3, b, w1);
    nand nand4(w4, w2, w3);
    nand nand5(w5, w4, c);
    nand nand6(w6, w5, w4);
    nand nand7(w7, w5, c);
    nand nand8(Sum, w6, w7);
    nand nand9(Carry, w1, w5);

endmodule

// --------- Testbench ---------
module test_full_adder_using_nand;
    reg a, b, c;
    wire Sum, Carry;

    full_adder_using_nand uut (.a(a), .b(b), .c(c), .Sum(Sum), .Carry(Carry));

    initial begin
        $dumpfile("full_adder_using_nand.vcd");
        $dumpvars(0, test_full_adder_using_nand);
    end


    initial begin
        $display("a b c | Sum Carry");
        $display("--------------");

        $monitor("%b %b %b | %b %b", a, b, c, Sum, Carry);
        a=0; b=0; c=0; #10;
        a=0; b=0; c=1; #10;
        a=0; b=1; c=0; #10;
        a=0; b=1; c=1; #10;
        a=1; b=0; c=0; #10;
        a=1; b=0; c=1; #10;
        a=1; b=1; c=0; #10;
        a=1; b=1; c=1; #10;

        // a=0; b=0; c=0; #10; $display("%b %b %b | %b %b", a, b, c, Sum, Carry);
        // a=0; b=0; c=1; #10; $display("%b %b %b | %b %b", a, b, c, Sum, Carry);
        // a=0; b=1; c=0; #10; $display("%b %b %b | %b %b", a, b, c, Sum, Carry);
        // a=0; b=1; c=1; #10; $display("%b %b %b | %b %b", a, b, c, Sum, Carry);
        // a=1; b=0; c=0; #10; $display("%b %b %b | %b %b", a, b, c, Sum, Carry);
        // a=1; b=0; c=1; #10; $display("%b %b %b | %b %b", a, b, c, Sum, Carry);
        // a=1; b=1; c=0; #10; $display("%b %b %b | %b %b", a, b, c, Sum, Carry);
        // a=1; b=1; c=1; #10; $display("%b %b %b | %b %b", a, b, c, Sum, Carry);

        $finish;
    end
endmodule

Codes/Verilog/build/full_adder_using_nand.vcd
$date
	Sat Sep 13 11:07:18 2025
$end
$version
	Icarus Verilog
$end
$timescale
	1s
$end
$scope module test_full_adder_using_nand $end
$var wire 1 ! Sum $end
$var wire 1 " Carry $end
$var reg 1 # a $end
$var reg 1 $ b $end
$var reg 1 % c $end
$scope module uut $end
$var wire 1 " Carry $end
$var wire 1 ! Sum $end
$var wire 1 # a $end
$var wire 1 $ b $end
$var wire 1 % c $end
$var wire 1 & w1 $end
$var wire 1 ' w2 $end
$var wire 1 ( w3 $end
$var wire 1 ) w4 $end
$var wire 1 * w5 $end
$var wire 1 + w6 $end
$var wire 1 , w7 $end
$upscope $end
$upscope $end
$enddefinitions $end
$comment Show the parameter values. $end
$dumpall
$end
#0
$dumpvars
1,
1+
1*
0)
1(
1'
1&
0%
0$
0#
0"
0!
$end
#10
1!
0,
1%
#20
0+
1!
1)
1,
0(
0%
1$
#30
0!
1+
1"
0*
1,
1%
#40
1!
0+
0"
1*
1(
0'
0%
0$
1#
#50
0!
1+
1"
0*
1,
1%
#60
0!
0)
1+
1'
1*
0&
1(
0%
1$
#70
1!
0,
1%
