Codes/Verilog/code2.v
module full_adder(input a, input b, input cin, output sum, output cout);
  assign sum  = a ^ b ^ cin;                            
  assign cout = (a & b) | (b & cin) | (a & cin);        
endmodule

module test_full_adder;
  reg a, b, cin;
  wire sum, cout;

  full_adder uut (.a(a), .b(b), .cin(cin), .sum(sum), .cout(cout));

  initial begin
    $dumpfile("full_adder.vcd");
    $dumpvars(0, test_full_adder);
  end

  initial begin
    $display("A B Cin | Sum Cout");
    $display("-------------------");
    a = 0; b = 0; cin = 0; #10; $display("%b %b  %b  |  %b    %b", a, b, cin, sum, cout);
    a = 0; b = 0; cin = 1; #10; $display("%b %b  %b  |  %b    %b", a, b, cin, sum, cout);
    a = 0; b = 1; cin = 0; #10; $display("%b %b  %b  |  %b    %b", a, b, cin, sum, cout);
    a = 0; b = 1; cin = 1; #10; $display("%b %b  %b  |  %b    %b", a, b, cin, sum, cout);
    a = 1; b = 0; cin = 0; #10; $display("%b %b  %b  |  %b    %b", a, b, cin, sum, cout);
    a = 1; b = 0; cin = 1; #10; $display("%b %b  %b  |  %b    %b", a, b, cin, sum, cout);
    a = 1; b = 1; cin = 0; #10; $display("%b %b  %b  |  %b    %b", a, b, cin, sum, cout);
    a = 1; b = 1; cin = 1; #10; $display("%b %b  %b  |  %b    %b", a, b, cin, sum, cout);
    $finish;
  end
endmodule

Codes/Verilog/build/full_adder.vcd
$date
	Fri Sep 12 10:28:57 2025
$end
$version
	Icarus Verilog
$end
$timescale
	1s
$end
$scope module test_full_adder $end
$var wire 1 ! sum $end
$var wire 1 " cout $end
$var reg 1 # a $end
$var reg 1 $ b $end
$var reg 1 % cin $end
$scope module uut $end
$var wire 1 # a $end
$var wire 1 $ b $end
$var wire 1 % cin $end
$var wire 1 " cout $end
$var wire 1 ! sum $end
$upscope $end
$upscope $end
$enddefinitions $end
$comment Show the parameter values. $end
$dumpall
$end
#0
$dumpvars
0%
0$
0#
0"
0!
$end
#10
1!
1%
#20
0%
1$
#30
1"
0!
1%
#40
0"
1!
0%
0$
1#
#50
1"
0!
1%
#60
0%
1$
#70
1!
1%
