Codes/Verilog/jkflipflop.v
module jk_flipflop (
    input wire J,
    input wire K,
    input wire clk,
    input wire reset,
    output reg Q,
    output reg Qn
);

always @(posedge clk or posedge reset) begin
    if (reset) begin
        Q  <= 0;
        Qn <= 1;
    end else begin
        case ({J, K})
            2'b00: begin
                // hold (do nothing)
            end
            2'b01: begin
                Q  <= 0;
                Qn <= 1;
            end
            2'b10: begin
                Q  <= 1;
                Qn <= 0;
            end
            2'b11: begin
                Q  <= ~Q;
                Qn <= ~Qn;
            end
        endcase
    end
end

endmodule

module tb_jk_flipflop;
    reg J;
    reg K;
    reg clk;
    reg reset;
    wire Q;
    wire Qn;

    jk_flipflop uut (
        .J(J),
        .K(K),
        .clk(clk),
        .reset(reset),
        .Q(Q),
        .Qn(Qn)
    );

    initial begin
        clk = 0;
        reset = 1;
        J = 0;
        K = 0;
        #12 reset = 0;
    end

    always #5 clk = ~clk;

    initial begin
        $dumpfile("jk_flipflop.vcd");
        $dumpvars(0, tb_jk_flipflop);
    end

    initial begin
        $display("Time\tclk\tJ K\tQ Qn");
        $monitor("%0t\t%b\t%b %b\t%b %b", $time, clk, J, K, Q, Qn);

        @(posedge clk); 
        @(posedge clk); J = 1; K = 0;
        @(posedge clk); J = 0; K = 1;
        @(posedge clk); J = 1; K = 1;
        @(posedge clk); J = 0; K = 0;
        @(posedge clk); J = 1; K = 1;
        @(posedge clk); J = 1; K = 1;
        @(posedge clk); $finish;
    end

endmodule

Codes/Verilog/build/jk_flipflop.vcd
$date
	Fri Oct 17 10:51:44 2025
$end
$version
	Icarus Verilog
$end
$timescale
	1s
$end
$scope module tb_jk_flipflop $end
$var wire 1 ! Qn $end
$var wire 1 " Q $end
$var reg 1 # J $end
$var reg 1 $ K $end
$var reg 1 % clk $end
$var reg 1 & reset $end
$scope module uut $end
$var wire 1 # J $end
$var wire 1 $ K $end
$var wire 1 % clk $end
$var wire 1 & reset $end
$var reg 1 " Q $end
$var reg 1 ! Qn $end
$upscope $end
$upscope $end
$enddefinitions $end
$comment Show the parameter values. $end
$dumpall
$end
#0
$dumpvars
1&
0%
0$
0#
0"
1!
$end
#5
1%
#10
0%
#12
0&
#15
0!
1"
1#
1%
#20
0%
#25
1!
0"
1$
0#
1%
#30
0%
#35
0!
1"
1#
1%
#40
0%
#45
0$
0#
1%
#50
0%
#55
1!
0"
1$
1#
1%
#60
0%
#65
0!
1"
1%
#70
0%
#75
1!
0"
1%
