Codes/Verilog/mux_8x1.v
module mux (
    input [0:7]i,
    input [0:2]s,
    output y
);

    wire w1,w2,w3,w4,w5,w6,w7,w8;
    assign w1 = i[0]&(~s[0])&(~s[1])&(~s[2]);
    assign w2 = i[1]&(~s[0])&(~s[1])&(s[2]);
    assign w3 = i[2]&(~s[0])&(s[1])&(~s[2]);
    assign w4 = i[3]&(~s[0])&(s[1])&(s[2]);
    assign w5 = i[4]&(s[0])&(~s[1])&(~s[2]);
    assign w6 = i[5]&(s[0])&(~s[1])&(s[2]);
    assign w7 = i[6]&(s[0])&(s[1])&(~s[2]);
    assign w8 = i[7]&(s[0])&(s[1])&(s[2]);
    assign y = w1|w2|w3|w4|w5|w6|w7|w8;
endmodule


`timescale 1ns / 1ps

module tb_mux;

    reg [0:7] i;
    reg [0:2] s;
    wire y;

    mux uut (
        i,s,y
    );

    initial begin
        $dumpfile("mux.vcd");      
        $dumpvars(0, tb_mux);      

        $display("Input\tSel\tY");   
        $monitor("%b\t%b\t%b", i, s, y);

        i = 8'b10000000; s = 3'b000; #10;
        i = 8'b00000000; s = 3'b001; #10;
        i = 8'b00100000; s = 3'b010; #10;
        i = 8'b00010000; s = 3'b011; #10;
        i = 8'b00000000; s = 3'b100; #10;
        i = 8'b00000100; s = 3'b101; #10;
        i = 8'b00000000; s = 3'b110; #10;
        i = 8'b00000001; s = 3'b111; #10;

        $finish;
    end

endmodule

Codes/Verilog/build/mux.vcd
$date
	Fri Sep 26 11:35:12 2025
$end
$version
	Icarus Verilog
$end
$timescale
	1ps
$end
$scope module tb_mux $end
$var wire 1 ! y $end
$var reg 8 " i [0:7] $end
$var reg 3 # s [0:2] $end
$scope module uut $end
$var wire 8 $ i [0:7] $end
$var wire 3 % s [0:2] $end
$var wire 1 & w1 $end
$var wire 1 ' w2 $end
$var wire 1 ( w3 $end
$var wire 1 ) w4 $end
$var wire 1 * w5 $end
$var wire 1 + w6 $end
$var wire 1 , w7 $end
$var wire 1 - w8 $end
$var wire 1 ! y $end
$upscope $end
$upscope $end
$enddefinitions $end
$comment Show the parameter values. $end
$dumpall
$end
#0
$dumpvars
0-
0,
0+
0*
0)
0(
0'
1&
b0 %
b10000000 $
b0 #
b10000000 "
1!
$end
#10000
0!
0&
b1 #
b1 %
b0 "
b0 $
#20000
1!
1(
b10 #
b10 %
b100000 "
b100000 $
#30000
1)
0(
b11 #
b11 %
b10000 "
b10000 $
#40000
0!
0)
b100 #
b100 %
b0 "
b0 $
#50000
1!
1+
b101 #
b101 %
b100 "
b100 $
#60000
0!
0+
b110 #
b110 %
b0 "
b0 $
#70000
1!
1-
b111 #
b111 %
b1 "
b1 $
