Codes/Verilog/booth2.v
`timescale 1ns/1ps

/* ================= DATAPATH ================= */

module boothmultiplier(
  LdA, LdQ, LdM, clrA, clrQ, clrff,
  sftA, sftQ, addsub, ldcnt, decr,
  data_in, clk, q0, qm1, eqz
);

input LdA, LdQ, LdM, clrA, clrQ, clrff;
input sftA, sftQ, addsub, ldcnt, decr, clk;
input [15:0] data_in;

output q0, qm1, eqz;

wire [15:0] A, Q, M, Z;
reg  [4:0] count;

initial count = 5'd0;

assign q0  = Q[0];
assign eqz = (count == 0);

shiftreg AR (LdA, clrA, Z, sftA, A, clk, A[15]);
shiftreg QR (LdQ, clrQ, data_in, sftQ, Q, clk, A[0]);
PIPO     MR (LdM, clrA, data_in, M, clk);
dff      QM1(Q[0], qm1, clk, clrff);
addsum   AS (Z, A, M, addsub);

always @(posedge clk) begin
  if (ldcnt)
    count <= 5'd16;
  else if (decr)
    count <= count - 1;
end

endmodule


/* ================= BASIC BLOCKS ================= */

module shiftreg(ld, clr, din, sft, dout, clk, s_in);
input ld, clr, sft, clk, s_in;
input [15:0] din;
output reg [15:0] dout;

always @(posedge clk) begin
  if (clr)
    dout <= 16'd0;
  else if (ld)
    dout <= din;
  else if (sft)
    dout <= {s_in, dout[15:1]};
end
endmodule


module PIPO(ld, clr, din, dout, clk);
input ld, clr, clk;
input [15:0] din;
output reg [15:0] dout;

always @(posedge clk) begin
  if (clr)
    dout <= 16'd0;
  else if (ld)
    dout <= din;
end
endmodule


module dff(d, q, clk, clr);
input d, clk, clr;
output reg q;

always @(posedge clk) begin
  if (clr)
    q <= 1'b0;
  else
    q <= d;
end
endmodule


module addsum(out, in1, in2, addsub);
input [15:0] in1, in2;
input addsub;
output reg [15:0] out;

always @(*) begin
  if (addsub)
    out = in1 + in2;
  else
    out = in1 + (~in2 + 1);
end
endmodule


/* ================= CONTROLLER ================= */

module controller(
  LdA, LdQ, LdM, clrA, clrQ, clrff,
  sftA, sftQ, addsub, ldcnt, decr,
  done, clk, Q0, qm1, eqz, start
);

input clk, Q0, qm1, eqz, start;
output reg LdA, LdQ, LdM, clrA, clrQ, clrff;
output reg sftA, sftQ, addsub, ldcnt, decr, done;

reg [2:0] state;

parameter s0=3'b000, s1=3'b001, s2=3'b010,
          s3=3'b011, s4=3'b100, s5=3'b101, s6=3'b110;

initial state = s0;

always @(posedge clk) begin
  case (state)
    s0: if (start) state <= s1;
    s1: state <= s2;
    s2: begin
          if ({Q0,qm1} == 2'b01) state <= s3;
          else if ({Q0,qm1} == 2'b10) state <= s4;
          else state <= s5;
        end
    s3: state <= s5;
    s4: state <= s5;
    s5: if (eqz) state <= s6;
        else state <= s2;
    s6: state <= s6;
    default: state <= s0;
  endcase
end

always @(*) begin
  LdA=0; LdQ=0; LdM=0; clrA=0; clrQ=0; clrff=0;
  sftA=0; sftQ=0; addsub=0; ldcnt=0; decr=0; done=0;

  case (state)
    s1: begin
          clrA=1; clrQ=1; clrff=1;
          ldcnt=1; LdQ=1; LdM=1;
        end
    s3: begin LdA=1; addsub=1; end
    s4: begin LdA=1; addsub=0; end
    s5: begin sftA=1; sftQ=1; decr=1; end
    s6: begin done=1; end
  endcase
end

endmodule


/* ================= TESTBENCH ================= */

module BoothMultiplier_tb;

reg [15:0] data_in;
reg clk, start;
wire done;

wire LdA,LdQ,LdM,clrA,clrQ,clrff;
wire sftA,sftQ,addsub,ldcnt,decr;
wire q0,qm1,eqz;

boothmultiplier BM (
  LdA,LdQ,LdM,clrA,clrQ,clrff,
  sftA,sftQ,addsub,ldcnt,decr,
  data_in,clk,q0,qm1,eqz
);

controller CL (
  LdA,LdQ,LdM,clrA,clrQ,clrff,
  sftA,sftQ,addsub,ldcnt,decr,
  done,clk,q0,qm1,eqz,start
);

always #5 clk = ~clk;

initial begin
  clk = 0;
  start = 0;
  data_in = 0;

  #10 data_in = 16'd7;   // multiplier
  #10 start = 1;
  #10 start = 0;

  #500 $finish;
end

initial begin
  $dumpfile("booth.vcd");
  $dumpvars(0, BoothMultiplier_tb);
end

endmodule

Codes/Verilog/booth.vcd
$date
	Tue Feb 10 12:22:59 2026
$end
$version
	Icarus Verilog
$end
$timescale
	1ps
$end
$scope module BoothMultiplier_tb $end
$var wire 1 ! sftQ $end
$var wire 1 " sftA $end
$var wire 1 # qm1 $end
$var wire 1 $ q0 $end
$var wire 1 % ldcnt $end
$var wire 1 & eqz $end
$var wire 1 ' done $end
$var wire 1 ( decr $end
$var wire 1 ) clrff $end
$var wire 1 * clrQ $end
$var wire 1 + clrA $end
$var wire 1 , addsub $end
$var wire 1 - LdQ $end
$var wire 1 . LdM $end
$var wire 1 / LdA $end
$var reg 1 0 clk $end
$var reg 16 1 data_in [15:0] $end
$var reg 1 2 start $end
$scope module BM $end
$var wire 1 0 clk $end
$var wire 16 3 data_in [15:0] $end
$var wire 1 ! sftQ $end
$var wire 1 " sftA $end
$var wire 1 # qm1 $end
$var wire 1 $ q0 $end
$var wire 1 % ldcnt $end
$var wire 1 & eqz $end
$var wire 1 ( decr $end
$var wire 1 ) clrff $end
$var wire 1 * clrQ $end
$var wire 1 + clrA $end
$var wire 1 , addsub $end
$var wire 16 4 Z [15:0] $end
$var wire 16 5 Q [15:0] $end
$var wire 16 6 M [15:0] $end
$var wire 1 - LdQ $end
$var wire 1 . LdM $end
$var wire 1 / LdA $end
$var wire 16 7 A [15:0] $end
$var reg 5 8 count [4:0] $end
$scope module AR $end
$var wire 1 0 clk $end
$var wire 1 9 s_in $end
$var wire 1 " sft $end
$var wire 1 / ld $end
$var wire 16 : din [15:0] $end
$var wire 1 + clr $end
$var reg 16 ; dout [15:0] $end
$upscope $end
$scope module AS $end
$var wire 16 < in1 [15:0] $end
$var wire 16 = in2 [15:0] $end
$var wire 1 , addsub $end
$var reg 16 > out [15:0] $end
$upscope $end
$scope module MR $end
$var wire 1 0 clk $end
$var wire 16 ? din [15:0] $end
$var wire 1 . ld $end
$var wire 1 + clr $end
$var reg 16 @ dout [15:0] $end
$upscope $end
$scope module QM1 $end
$var wire 1 0 clk $end
$var wire 1 A d $end
$var wire 1 ) clr $end
$var reg 1 # q $end
$upscope $end
$scope module QR $end
$var wire 1 0 clk $end
$var wire 16 B din [15:0] $end
$var wire 1 C s_in $end
$var wire 1 ! sft $end
$var wire 1 - ld $end
$var wire 1 * clr $end
$var reg 16 D dout [15:0] $end
$upscope $end
$upscope $end
$scope module CL $end
$var wire 1 $ Q0 $end
$var wire 1 0 clk $end
$var wire 1 & eqz $end
$var wire 1 # qm1 $end
$var wire 1 2 start $end
$var reg 1 / LdA $end
$var reg 1 . LdM $end
$var reg 1 - LdQ $end
$var reg 1 , addsub $end
$var reg 1 + clrA $end
$var reg 1 * clrQ $end
$var reg 1 ) clrff $end
$var reg 1 ( decr $end
$var reg 1 ' done $end
$var reg 1 % ldcnt $end
$var reg 1 " sftA $end
$var reg 1 ! sftQ $end
$var reg 3 E state [2:0] $end
$upscope $end
$upscope $end
$enddefinitions $end
#0
$dumpvars
b0 E
bx D
xC
b0 B
xA
bx @
b0 ?
bx >
bx =
bx <
bx ;
bx :
x9
b0 8
bx 7
bx 6
bx 5
bx 4
b0 3
02
b0 1
00
0/
0.
0-
0,
0+
0*
0)
0(
0'
1&
0%
x$
x#
0"
0!
$end
#5000
10
#10000
00
b111 1
b111 3
b111 ?
b111 B
#15000
10
#20000
00
12
#25000
1.
1-
1%
1)
1*
1+
b1 E
10
#30000
00
02
#35000
0%
0)
0*
0+
0.
0-
0A
0$
b0 4
b0 :
b0 >
0C
09
b10 E
0&
b10000 8
0#
b0 6
b0 =
b0 @
b0 5
b0 D
b0 7
b0 ;
b0 <
10
#40000
00
#45000
1(
1!
1"
b101 E
10
#50000
00
#55000
0(
0!
0"
b10 E
b1111 8
10
#60000
00
#65000
1(
1!
1"
b101 E
10
#70000
00
#75000
0(
0!
0"
b10 E
b1110 8
10
#80000
00
#85000
1(
1!
1"
b101 E
10
#90000
00
#95000
0(
0!
0"
b10 E
b1101 8
10
#100000
00
#105000
1(
1!
1"
b101 E
10
#110000
00
#115000
0(
0!
0"
b10 E
b1100 8
10
#120000
00
#125000
1(
1!
1"
b101 E
10
#130000
00
#135000
0(
0!
0"
b10 E
b1011 8
10
#140000
00
#145000
1(
1!
1"
b101 E
10
#150000
00
#155000
0(
0!
0"
b10 E
b1010 8
10
#160000
00
#165000
1(
1!
1"
b101 E
10
#170000
00
#175000
0(
0!
0"
b10 E
b1001 8
10
#180000
00
#185000
1(
1!
1"
b101 E
10
#190000
00
#195000
0(
0!
0"
b10 E
b1000 8
10
#200000
00
#205000
1(
1!
1"
b101 E
10
#210000
00
#215000
0(
0!
0"
b10 E
b111 8
10
#220000
00
#225000
1(
1!
1"
b101 E
10
#230000
00
#235000
0(
0!
0"
b10 E
b110 8
10
#240000
00
#245000
1(
1!
1"
b101 E
10
#250000
00
#255000
0(
0!
0"
b10 E
b101 8
10
#260000
00
#265000
1(
1!
1"
b101 E
10
#270000
00
#275000
0(
0!
0"
b10 E
b100 8
10
#280000
00
#285000
1(
1!
1"
b101 E
10
#290000
00
#295000
0(
0!
0"
b10 E
b11 8
10
#300000
00
#305000
1(
1!
1"
b101 E
10
#310000
00
#315000
0(
0!
0"
b10 E
b10 8
10
#320000
00
#325000
1(
1!
1"
b101 E
10
#330000
00
#335000
0(
0!
0"
b10 E
b1 8
10
#340000
00
#345000
1(
1!
1"
b101 E
10
#350000
00
#355000
0(
0!
0"
b10 E
1&
b0 8
10
#360000
00
#365000
1(
1!
1"
b101 E
10
#370000
00
#375000
1'
0(
0!
0"
b110 E
0&
b11111 8
10
