Codes/Verilog/mux.v
module mux2to1 (input A, input B, input S, output Y);

    wire nS, A1, B1;

    not  (nS, S);     
    and  (A1, A, nS); 
    and  (B1, B, S);  
    or   (Y, A1, B1); 

endmodule

module tb_mux2to1;
    reg A, B, S;   
    wire Y;        

    mux2to1 uut (.A(A),.B(B),.S(S),.Y(Y));

    initial begin
         $dumpfile("mux2to1.vcd");
        $dumpvars(0, tb_mux2to1);

        $monitor("A=%b B=%b S=%b -> Y=%b", A, B, S, Y);

        A=0; B=0; S=0; #10;  
        A=1; B=0; S=0; #10;  
        A=0; B=1; S=0; #10;  
        A=1; B=1; S=0; #10;  
        A=0; B=0; S=1; #10;  
        A=1; B=0; S=1; #10;  
        A=0; B=1; S=1; #10;  
        A=1; B=1; S=1; #10;  

        $finish;  
    end
endmodule

Codes/Verilog/mux2to1.vcd
$date
	Mon Feb 09 23:04:12 2026
$end
$version
	Icarus Verilog
$end
$timescale
	1s
$end
$scope module tb_mux2to1 $end
$var wire 1 ! Y $end
$var reg 1 " A $end
$var reg 1 # B $end
$var reg 1 $ S $end
$scope module uut $end
$var wire 1 " A $end
$var wire 1 % A1 $end
$var wire 1 # B $end
$var wire 1 & B1 $end
$var wire 1 $ S $end
$var wire 1 ! Y $end
$var wire 1 ' nS $end
$upscope $end
$upscope $end
$enddefinitions $end
#0
$dumpvars
1'
0&
0%
0$
0#
0"
0!
$end
#10
1!
1%
1"
#20
0!
0%
1#
0"
#30
1!
1%
1"
#40
0!
0'
0%
1$
0#
0"
#50
1"
#60
1!
1&
1#
0"
#70
1"
