Codes/Verilog/advancepipeline.v
module pipe5(zout,rs1,rs2,rd,func,addr,clk1,clk2);
input [3:0] rs1,rs2,rd;
input clk1,clk2;
input [3:0] func;
input [7:0] addr;
output [15:0] zout;

reg [15:0] regbank [15:0];
reg [15:0] membank [255:0];

reg [15:0] l1a,l1b;
reg [3:0]  l1rd,l1func;
reg [7:0]  l1add;

reg [15:0] l2a,l2b;
reg [3:0]  l2rd,l2func;
reg [7:0]  l2add;

reg [15:0] l3z;
reg [3:0]  l3rd;
reg [7:0]  l3add;

reg [15:0] l4z;
reg [3:0]  l4rd;
reg [7:0]  l4add;

reg [15:0] l5z;

assign zout = l5z;

always @(posedge clk1)
begin
    l1a   <= #2 regbank[rs1];
    l1b   <= #2 regbank[rs2];
    l1rd  <= #2 rd;
    l1func<= #2 func;
    l1add <= #2 addr;
end

always @(posedge clk2)
begin
    l2a   <= #2 l1a;
    l2b   <= #2 l1b;
    l2rd  <= #2 l1rd;
    l2func<= #2 l1func;
    l2add <= #2 l1add;
end

always @(posedge clk1)
begin
    case(l2func)
        0: l3z <= #2 l2a + l2b;
        1: l3z <= #2 l2a - l2b;
        2: l3z <= #2 l2a * l2b;
        3: l3z <= #2 l2a;
        4: l3z <= #2 l2b;
        5: l3z <= #2 l2a & l2b;
        6: l3z <= #2 l2a | l2b;
        7: l3z <= #2 l2a ^ l2b;
        8: l3z <= #2 ~l2a;
        9: l3z <= #2 ~l2b;
        10: l3z <= #2 l2a >> 1;
        11: l3z <= #2 l2b << 1;
        default: l3z <= 16'hxxxx;
    endcase
    l3rd  <= #2 l2rd;
    l3add <= #2 l2add;
end

always @(posedge clk2)
begin
    l4z   <= #2 l3z;
    l4rd  <= #2 l3rd;
    l4add <= #2 l3add;
    membank[l3add] <= #2 l3z;
end

always @(posedge clk1)
begin
    l5z <= #2 l4z;
    regbank[l4rd] <= #2 l4z;
end

endmodule

module simuli5();
reg [3:0] rs1,rs2,rd,func;
reg [7:0] addr;
wire [15:0] zout;
integer k;
reg clk1, clk2;

pipe5 uut(zout,rs1,rs2,rd,func,addr,clk1,clk2);

initial clk1=1;
initial clk2=0;
always #10 clk1=~clk1;
always #10 clk2=~clk2;

initial
begin
    for(k=0;k<16;k=k+1)
        uut.regbank[k]=k;
end

initial
begin
    $dumpfile("pipe5.vcd");
    $dumpvars(0, simuli5);

    $monitor("T=%0t | rs1=%d rs2=%d rd=%d func=%d addr=%d zout=%d",
             $time, rs1, rs2, rd, func, addr, zout);

    #20 rs1=6; rs2=1; rd=10; addr=125; func=2;
    #20 rs1=9; rs2=8; rd=12; addr=126; func=3;
    #20 rs1=2; rs2=4; rd=13; addr=125; func=4;
    #120 $finish;
end
endmodule

Codes/Verilog/pipe5.vcd
$date
	Wed Feb 18 10:55:09 2026
$end
$version
	Icarus Verilog
$end
$timescale
	1s
$end
$scope module simuli5 $end
$var wire 16 ! zout [15:0] $end
$var reg 8 " addr [7:0] $end
$var reg 1 # clk1 $end
$var reg 1 $ clk2 $end
$var reg 4 % func [3:0] $end
$var reg 4 & rd [3:0] $end
$var reg 4 ' rs1 [3:0] $end
$var reg 4 ( rs2 [3:0] $end
$var integer 32 ) k [31:0] $end
$scope module uut $end
$var wire 8 * addr [7:0] $end
$var wire 1 # clk1 $end
$var wire 1 $ clk2 $end
$var wire 4 + func [3:0] $end
$var wire 4 , rd [3:0] $end
$var wire 4 - rs1 [3:0] $end
$var wire 4 . rs2 [3:0] $end
$var wire 16 / zout [15:0] $end
$var reg 16 0 l1a [15:0] $end
$var reg 8 1 l1add [7:0] $end
$var reg 16 2 l1b [15:0] $end
$var reg 4 3 l1func [3:0] $end
$var reg 4 4 l1rd [3:0] $end
$var reg 16 5 l2a [15:0] $end
$var reg 8 6 l2add [7:0] $end
$var reg 16 7 l2b [15:0] $end
$var reg 4 8 l2func [3:0] $end
$var reg 4 9 l2rd [3:0] $end
$var reg 8 : l3add [7:0] $end
$var reg 4 ; l3rd [3:0] $end
$var reg 16 < l3z [15:0] $end
$var reg 8 = l4add [7:0] $end
$var reg 4 > l4rd [3:0] $end
$var reg 16 ? l4z [15:0] $end
$var reg 16 @ l5z [15:0] $end
$upscope $end
$upscope $end
$enddefinitions $end
#0
$dumpvars
bx @
bx ?
bx >
bx =
bx <
bx ;
bx :
bx 9
bx 8
bx 7
bx 6
bx 5
bx 4
bx 3
bx 2
bx 1
bx 0
bx /
bx .
bx -
bx ,
bx +
bx *
b10000 )
bx (
bx '
bx &
bx %
0$
1#
bx "
bx !
$end
#10
1$
0#
#20
0$
1#
b10 %
b10 +
b1111101 "
b1111101 *
b1010 &
b1010 ,
b1 (
b1 .
b110 '
b110 -
#22
b1111101 1
b10 3
b1010 4
b1 2
b110 0
#30
1$
0#
#32
b1111101 6
b10 8
b1010 9
b1 7
b110 5
#40
0$
1#
b11 %
b11 +
b1111110 "
b1111110 *
b1100 &
b1100 ,
b1000 (
b1000 .
b1001 '
b1001 -
#42
b1111110 1
b11 3
b1100 4
b1000 2
b1001 0
b1111101 :
b1010 ;
b110 <
#50
1$
0#
#52
b1111110 6
b11 8
b1100 9
b1000 7
b1001 5
b1111101 =
b1010 >
b110 ?
#60
0$
1#
b100 %
b100 +
b1111101 "
b1111101 *
b1101 &
b1101 ,
b100 (
b100 .
b10 '
b10 -
#62
b110 !
b110 /
b110 @
b1111110 :
b1100 ;
b1001 <
b1111101 1
b100 3
b1101 4
b100 2
b10 0
#70
1$
0#
#72
b1111110 =
b1100 >
b1001 ?
b1111101 6
b100 8
b1101 9
b100 7
b10 5
#80
0$
1#
#82
b1111101 :
b1101 ;
b100 <
b1001 !
b1001 /
b1001 @
#90
1$
0#
#92
b1111101 =
b1101 >
b100 ?
#100
0$
1#
#102
b100 !
b100 /
b100 @
