Codes/Verilog/pipeline.v
module pipe_ex (F, A, B, C, D, clk);
parameter N = 10;
input [N-1:0] A, B, C, D;
input clk;
output [N-1:0] F;
reg [N-1:0] L12_x1, L12_x2, L12_D, L23_x3, L23_D, L34_F;
assign F = L34_F;
always @(posedge clk)
    begin
        L12_x1 <= #4 A + B;
        L12_x2 <= #4 C - D;  
        L12_D  <=  D;
        L23_x3 <= #4 L12_x1 + L12_x2;
        L23_D  <= L12_D;
        L34_F  <= #6 L23_x3 * L23_D;
    end
endmodule


module tb_pipe_ex;

parameter N = 10;

reg  [N-1:0] A, B, C, D;
reg          clk;
wire [N-1:0] F;

pipe_ex #(N) dut (
    .F(F),
    .A(A),
    .B(B),
    .C(C),
    .D(D),
    .clk(clk)
);

always #5 clk = ~clk;

initial begin
    $dumpfile("pipeline.vcd");   
    $dumpvars(0, tb_pipe_ex);   
end

initial begin
    clk = 0;
    A = 0; B = 0; C = 0; D = 0;

    #10 A = 10; B = 5;  C = 3;  D = 2;
    #10 A = 20; B = 4;  C = 1;  D = 3;
    #10 A = 7;  B = 6;  C = 2;  D = 4;
    #10 A = 15; B = 8;  C = 5;  D = 2;

    #100 $finish;
end

initial begin
    $monitor("Time=%0t | A=%d B=%d C=%d D=%d | F=%d",
              $time, A, B, C, D, F);
end

endmodule

Codes/Verilog/pipeline.vcd
$date
	Tue Feb 17 11:42:22 2026
$end
$version
	Icarus Verilog
$end
$timescale
	1s
$end
$scope module tb_pipe_ex $end
$var wire 10 ! F [9:0] $end
$var reg 10 " A [9:0] $end
$var reg 10 # B [9:0] $end
$var reg 10 $ C [9:0] $end
$var reg 10 % D [9:0] $end
$var reg 1 & clk $end
$scope module dut $end
$var wire 10 ' A [9:0] $end
$var wire 10 ( B [9:0] $end
$var wire 10 ) C [9:0] $end
$var wire 10 * D [9:0] $end
$var wire 10 + F [9:0] $end
$var wire 1 & clk $end
$var reg 10 , L12_D [9:0] $end
$var reg 10 - L12_x1 [9:0] $end
$var reg 10 . L12_x2 [9:0] $end
$var reg 10 / L23_D [9:0] $end
$var reg 10 0 L23_x3 [9:0] $end
$var reg 10 1 L34_F [9:0] $end
$upscope $end
$upscope $end
$enddefinitions $end
#0
$dumpvars
bx 1
bx 0
bx /
bx .
bx -
bx ,
bx +
b0 *
b0 )
b0 (
b0 '
0&
b0 %
b0 $
b0 #
b0 "
bx !
$end
#5
b0 ,
1&
#9
b0 .
b0 -
#10
0&
b10 %
b10 *
b11 $
b11 )
b101 #
b101 (
b1010 "
b1010 '
#15
b0 /
b10 ,
1&
#19
b0 0
b1 .
b1111 -
#20
0&
b11 %
b11 *
b1 $
b1 )
b100 #
b100 (
b10100 "
b10100 '
#25
b10 /
b11 ,
1&
#29
b10000 0
b1111111110 .
b11000 -
#30
0&
b100 %
b100 *
b10 $
b10 )
b110 #
b110 (
b111 "
b111 '
#31
b0 !
b0 +
b0 1
#35
b11 /
b100 ,
1&
#39
b10110 0
b1101 -
#40
0&
b10 %
b10 *
b101 $
b101 )
b1000 #
b1000 (
b1111 "
b1111 '
#41
b100000 !
b100000 +
b100000 1
#45
b100 /
b10 ,
1&
#49
b1011 0
b11 .
b10111 -
#50
0&
#51
b1000010 !
b1000010 +
b1000010 1
#55
b10 /
1&
#59
b11010 0
#60
0&
#61
b101100 !
b101100 +
b101100 1
#65
1&
#70
0&
#71
b110100 !
b110100 +
b110100 1
