Codes/Verilog/ripple_carry_adder.v
`timescale 1ns/1ps

module ripple_carry_adder #(parameter N = 8)(
    input  [N-1:0] A,
    input  [N-1:0] B,
    input          Cin,
    output [N-1:0] Sum,
    output         Cout
);

    wire [N:0] carry;
    assign carry[0] = Cin;

    genvar i;
    generate
        for(i = 0; i < N; i = i + 1) begin : RCA
            assign {carry[i+1], Sum[i]} = A[i] + B[i] + carry[i];
        end
    endgenerate

    assign Cout = carry[N];

endmodule

Codes/Verilog/rca_top.v
module rca_top(
    input clk,
    input [7:0] A,
    input [7:0] B,
    input Cin,
    output reg [7:0] Sum,
    output reg Cout
);

wire [7:0] Sum_temp;
wire Cout_temp;

ripple_carry_adder #(8) uut (
    .A(A),
    .B(B),
    .Cin(Cin),
    .Sum(Sum_temp),
    .Cout(Cout_temp)
);

always @(posedge clk) begin
    Sum <= Sum_temp;
    Cout <= Cout_temp;
end

endmodule

Codes/Verilog/tb_rca_top.v
`timescale 1ns/1ps

module tb_rca_top;

    parameter N = 8;

    // DUT signals
    reg          clk;
    reg  [N-1:0] A, B;
    reg          Cin;
    wire [N-1:0] Sum;
    wire         Cout;

    // Instantiate the sequential (clocked) RCA top
    rca_top uut (
        .clk (clk),
        .A   (A),
        .B   (B),
        .Cin (Cin),
        .Sum (Sum),
        .Cout(Cout)
    );

    // Clock generation: 10 ns period (50 MHz)
    initial clk = 0;
    always #5 clk = ~clk;

    // Task: apply inputs, wait one full clock cycle, then display result
    task apply_and_check;
        input [N-1:0] a_in, b_in;
        input         cin_in;
        begin
            A   = a_in;
            B   = b_in;
            Cin = cin_in;
            @(posedge clk);   // inputs are registered on this edge
            #1;               // small delay so outputs settle after clock edge
            $display("A=%0d  B=%0d  Cin=%b  |  Sum=%0d  Cout=%b  (Expected: %0d)",
                     A, B, Cin, Sum, Cout, A + B + Cin);
        end
    endtask

    initial begin
        $dumpfile("rca_top.vcd");
        $dumpvars(0, tb_rca_top);

        $display("=== Sequential RCA Top Testbench ===");
        $display("A\t\tB\t\tCin\t|\tSum\t\tCout");
        $display("--------------------------------------------------------------");

        // Apply test vectors; outputs appear ONE clock after inputs are applied
        apply_and_check(8'd5,   8'd3,   1'b0);   // 5  + 3   = 8
        apply_and_check(8'd15,  8'd1,   1'b0);   // 15 + 1   = 16
        apply_and_check(8'd255, 8'd1,   1'b0);   // 255 + 1  = 0 (overflow, Cout=1)
        apply_and_check(8'd100, 8'd50,  1'b1);   // 100 + 50 + 1 = 151
        apply_and_check(8'd128, 8'd127, 1'b1);   // 128 + 127 + 1 = 0 (overflow, Cout=1)
        apply_and_check(8'd0,   8'd0,   1'b0);   // 0  + 0   = 0

        $display("=== Simulation Complete ===");
        $finish;
    end

endmodule

Codes/Verilog/rca_top.vcd
$date
	Thu Apr 16 23:03:00 2026
$end
$version
	Icarus Verilog
$end
$timescale
	1ps
$end
$scope module tb_rca_top $end
$var wire 8 ! Sum [7:0] $end
$var wire 1 " Cout $end
$var reg 8 # A [7:0] $end
$var reg 8 $ B [7:0] $end
$var reg 1 % Cin $end
$var reg 1 & clk $end
$scope module uut $end
$var wire 8 ' A [7:0] $end
$var wire 8 ( B [7:0] $end
$var wire 1 % Cin $end
$var wire 1 & clk $end
$var wire 8 ) Sum_temp [7:0] $end
$var wire 1 * Cout_temp $end
$var reg 1 " Cout $end
$var reg 8 + Sum [7:0] $end
$scope module uut $end
$var wire 8 , A [7:0] $end
$var wire 8 - B [7:0] $end
$var wire 1 % Cin $end
$var wire 9 . carry [8:0] $end
$var wire 8 / Sum [7:0] $end
$var wire 1 * Cout $end
$scope begin RCA[0] $end
$upscope $end
$scope begin RCA[1] $end
$upscope $end
$scope begin RCA[2] $end
$upscope $end
$scope begin RCA[3] $end
$upscope $end
$scope begin RCA[4] $end
$upscope $end
$scope begin RCA[5] $end
$upscope $end
$scope begin RCA[6] $end
$upscope $end
$scope begin RCA[7] $end
$upscope $end
$upscope $end
$upscope $end
$scope task apply_and_check $end
$var reg 8 0 a_in [7:0] $end
$var reg 8 1 b_in [7:0] $end
$var reg 1 2 cin_in $end
$upscope $end
$upscope $end
$enddefinitions $end
#0
$dumpvars
02
b11 1
b101 0
b1000 /
b1110 .
b11 -
b101 ,
bx +
0*
b1000 )
b11 (
b101 '
0&
0%
b11 $
b101 #
x"
bx !
$end
#5000
0"
b1000 !
b1000 +
1&
#6000
b10000 )
b10000 /
b11110 .
b1 $
b1 (
b1 -
b1111 #
b1111 '
b1111 ,
b1 1
b1111 0
#10000
0&
#15000
b10000 !
b10000 +
1&
#16000
1*
b111111110 .
b0 )
b0 /
b11111111 #
b11111111 '
b11111111 ,
b11111111 0
#20000
0&
#25000
1"
b0 !
b0 +
1&
#26000
0*
b10010111 )
b10010111 /
b11000001 .
1%
b110010 $
b110010 (
b110010 -
b1100100 #
b1100100 '
b1100100 ,
12
b110010 1
b1100100 0
#30000
0&
#35000
0"
b10010111 !
b10010111 +
1&
#36000
1*
b0 )
b0 /
b111111111 .
b1111111 $
b1111111 (
b1111111 -
b10000000 #
b10000000 '
b10000000 ,
b1111111 1
b10000000 0
#40000
0&
#45000
1"
b0 !
b0 +
1&
#46000
0*
b0 )
b0 /
b0 .
0%
b0 $
b0 (
b0 -
b0 #
b0 '
b0 ,
02
b0 1
b0 0
#50000
0&
#55000
0"
1&
